pikas/__init__.py
pikas/ensemble/bagging.py
pikas/ensemble/sklearn.py
pikas/ensemble/tests/test_sklearn.py
pikas-0.1.0.dist-info/WHEEL
pikas-0.1.0.dist-info/METADATA
pikas-0.1.0.dist-info/RECORD
