Metadata-Version: 2.1
Name: pikas
Version: 0.1.0
Summary: A machine learning framework for exploring tree ensemble algorithms.
Author: Stephanos Stephani
Author-email: stephanos.stephani@gmail.com
Requires-Python: >=3.7,<4.0
Classifier: Programming Language :: Python :: 3
Classifier: Programming Language :: Python :: 3.7
Classifier: Programming Language :: Python :: 3.8
Classifier: Programming Language :: Python :: 3.9
Requires-Dist: scikit-learn (>=0.24.0,<0.25.0)
